somap-0.1.1.dist-info/METADATA
somap-0.1.1.dist-info/WHEEL
somap-0.1.1.dist-info/licenses/LICENSE
somap/__init__.py
somap/config.py
somap/core.py
somap/datasets/__init__.py
somap/datasets/base.py
somap/datasets/mnist.py
somap/datasets/utils.py
somap/distance.py
somap/grid.py
somap/learning_rate.py
somap/neighborhood.py
somap/plot.py
somap/plot_backends/__init__.py
somap/plot_backends/altair.py
somap/plot_backends/array2image.py
somap/plot_backends/base.py
somap/plot_backends/resources/Carlito-Regular.ttf
somap/plot_backends/utils.py
somap/serialisation.py
somap/som.py
somap/update.py
somap/utils.py
somap-0.1.1.dist-info/RECORD
