Metadata-Version: 2.1
Name: somap
Version: 0.1.1
Summary: Self-Organizing Maps in python
Author-Email: Matthieu Thiboust <14574229+mthiboust@users.noreply.github.com>
License: Apache 2.0
Project-URL: Repository, https://github.com/mthiboust/somap
Project-URL: Documentation, https://mthiboust.github.io/somap/
Requires-Python: <3.12,>=3.10
Requires-Dist: jax>=0.4.20
Requires-Dist: equinox>=0.11.1
Requires-Dist: jaxtyping>=0.2.23
Requires-Dist: beartype>=0.16.4
Requires-Dist: datasets>=2.14.6
Requires-Dist: matplotlib>=3.8.0
Requires-Dist: altair>=5.1.2
Requires-Dist: vl-convert-python>=1.0.0
Requires-Dist: colormap2d>=0.1.3
Requires-Dist: array2image>=0.1.0
Requires-Dist: ipykernel>=6.26.0; extra == "notebook"
Requires-Dist: ipywidgets>=8.1.1; extra == "notebook"
Requires-Dist: python-dotenv>=1.0.0; extra == "notebook"
Requires-Dist: pytest>=7.4.3; extra == "dev"
Requires-Dist: ruff>=0.1.5; extra == "dev"
Requires-Dist: mkdocs-material>=9.4.11; extra == "docs"
Requires-Dist: mknotebooks>=0.8.0; extra == "docs"
Requires-Dist: mkdocstrings[crystal,python]>=0.24.0; extra == "docs"
Requires-Dist: pytkdocs-tweaks>=0.0.7; extra == "docs"
Provides-Extra: notebook
Provides-Extra: dev
Provides-Extra: docs
